Metadata-Version: 1.0
Name: parenclitic
Version: 0.1.2
Summary: Parenclitic approach with kernels inside
Home-page: https://github.com/mike-live/parenclitic
Author: Mikhail Krivonosov
Author-email: mike_live@mail.ru
License: MIT
Platform: UNKNOWN
